pxpip/__init__.py
pxpip/__main__.py
pxpip/classes.py
pxpip/common.py
pxpip/logger.py
pxpip/parser.py
pxpip/s3_facade.py
pxpip-0.0.2.dist-info/LICENSE
pxpip-0.0.2.dist-info/METADATA
pxpip-0.0.2.dist-info/WHEEL
pxpip-0.0.2.dist-info/entry_points.txt
pxpip-0.0.2.dist-info/top_level.txt
pxpip-0.0.2.dist-info/RECORD
